setup.py
quiver_engine/__init__.py
quiver_engine/imagenet_utils.py
quiver_engine/layer_result_generators.py
quiver_engine/server.py
quiver_engine/util.py
quiver_vis.egg-info/PKG-INFO
quiver_vis.egg-info/SOURCES.txt
quiver_vis.egg-info/dependency_links.txt
quiver_vis.egg-info/requires.txt
quiver_vis.egg-info/top_level.txt