Metadata-Version: 1.0
Name: quiver-vis
Version: 0.1
Summary: Interactive per-layer visualization for convents in keras
Home-page: UNKNOWN
Author: Jake Bian
Author-email: jake@keplr.io
License: mit
Platform: UNKNOWN
